{
  "type": "create:mixing",
  "heatRequirement": "heated",
  "ingredients": [
    {
      "tag": "forge:plates/copper"
    },
    {
      "tag": "forge:plates/zinc"
    },
    {
      "fluid": "createconquer:molten_nickel_sulfate_fluid",
      "amount": 25
    }
  ],
  "results": [
    {
      "item": "createconquer:sulfate_crystal"
    },
    {
      "item": "create:copper_sheet"
    },
    {
      "item": "createconquer:zinc_plate"
    },
    {
      "item": "createconquer:nickel_powder"
    }

  ]
}